Protoss_Pylon
Protoss_Gateway
Protoss_Pylon
Protoss_Gateway
Protoss_Assimilator
Protoss_Forge
Protoss_Pylon
Protoss_Cybernetics_Core
Protoss_Photon_Cannon
Protoss_Gateway
Protoss_Pylon
Protoss_Robotics_Facility
Protoss_Citadel_of_Adun
Protoss_Nexus
Protoss_Pylon
Protoss_Observatory
Protoss_Templar_Archives
Protoss_Photon_Cannon
Protoss_Stargate
Protoss_Gateway
Protoss_Stargate
Protoss_Arbiter_Tribunal
Protoss_Gateway
Protoss_Photon_Cannon
Protoss_Photon_Cannon
